gtb.py
setup.py
gtb.egg-info/PKG-INFO
gtb.egg-info/SOURCES.txt
gtb.egg-info/dependency_links.txt
gtb.egg-info/requires.txt
gtb.egg-info/top_level.txt