Metadata-Version: 1.0
Name: gtb
Version: 0.0.1421587592
Summary: Tools for inspecting running greenlets and getting tracebacks
Home-page: UNKNOWN
Author: Mike Lang
Author-email: mikelang3000@gmail.com
License: UNKNOWN
Platform: UNKNOWN
